firstrade/__init__.py
firstrade/account.py
firstrade/exceptions.py
firstrade/order.py
firstrade/symbols.py
firstrade/urls.py
firstrade-0.0.34.dist-info/licenses/LICENSE
firstrade-0.0.34.dist-info/METADATA
firstrade-0.0.34.dist-info/WHEEL
firstrade-0.0.34.dist-info/top_level.txt
firstrade-0.0.34.dist-info/RECORD
