Metadata-Version: 2.4
Name: firstrade
Version: 0.0.34
Summary: An unofficial API for Firstrade
Home-page: https://github.com/MaxxRK/firstrade-api
Download-URL: https://github.com/MaxxRK/firstrade-api/archive/refs/tags/0034.tar.gz
Author: MaxxRK
Author-email: maxxrk@pm.me
License: MIT
Keywords: FIRSTRADE,API
Classifier: Development Status :: 3 - Alpha
Classifier: Intended Audience :: Developers
Classifier: Topic :: Internet :: WWW/HTTP :: Session
Classifier: License :: OSI Approved :: MIT License
Classifier: Programming Language :: Python :: 3
Classifier: Programming Language :: Python :: 3.8
Classifier: Programming Language :: Python :: 3.9
Classifier: Programming Language :: Python :: 3.10
Classifier: Programming Language :: Python :: 3.11
Classifier: Programming Language :: Python :: 3.12
Classifier: Programming Language :: Python :: 3.13
License-File: LICENSE
Requires-Dist: requests
Requires-Dist: beautifulsoup4
Requires-Dist: lxml
Dynamic: author
Dynamic: author-email
Dynamic: classifier
Dynamic: description
Dynamic: description-content-type
Dynamic: download-url
Dynamic: home-page
Dynamic: keywords
Dynamic: license
Dynamic: license-file
Dynamic: requires-dist
Dynamic: summary
